{
  "users": [
    {
      "id": 1,
      "username": "Alverta.Beatty",
      "password": "tvgydQZpg1tUkjE",
      "email": "Scot_Miller78@hotmail.com"
    },
    {
      "id": 2,
      "username": "Vaughn.Streich98",
      "password": "mVEb2Y9LqmjfqIG",
      "email": "Imani_Turner91@hotmail.com"
    },
    {
      "id": 3,
      "username": "Oran54",
      "password": "6C1hF3iqBz64jKy",
      "email": "Kianna22@gmail.com"
    },
    {
      "id": 4,
      "username": "Arnulfo_Feest",
      "password": "EG3rF9GWGZLim3t",
      "email": "Isabella.OKon39@gmail.com"
    },
    {
      "id": 5,
      "username": "Elda_Dare36",
      "password": "mn0hx56Tt7UJXIj",
      "email": "Ricardo_Hane@hotmail.com"
    },
    {
      "id": 6,
      "username": "Shanon30",
      "password": "rkNFflVjAly1leR",
      "email": "Estel_Erdman@hotmail.com"
    },
    {
      "id": 7,
      "username": "Rod61",
      "password": "5bBKnyOKUKN7062",
      "email": "Carroll.Yost@gmail.com"
    },
    {
      "id": 8,
      "username": "Rodrick94",
      "password": "97OonvxNExXL7Zf",
      "email": "Kaya.Torp50@gmail.com"
    },
    {
      "id": 9,
      "username": "Hillary.Gibson85",
      "password": "nC9qpvGSJpEC85G",
      "email": "Constance_Windler86@hotmail.com"
    },
    {
      "id": 10,
      "username": "Shannon.Nitzsche90",
      "password": "IKJeCw1PNW_9Ed6",
      "email": "Hillary21@hotmail.com"
    },
    {
      "id": 11,
      "username": "Ryann_Greenholt",
      "password": "oQbnutuTwBVxWOc",
      "email": "Mathilde81@gmail.com"
    },
    {
      "id": 12,
      "username": "Elmore_Koelpin37",
      "password": "w5Tp5_GA16d3ukX",
      "email": "Sydnee11@yahoo.com"
    },
    {
      "id": 13,
      "username": "Hailee.Borer66",
      "password": "i6mwl1RxO5clW4a",
      "email": "Reece_Abernathy59@yahoo.com"
    },
    {
      "id": 14,
      "username": "Claudia_Little",
      "password": "PBFVFKvN80MvCZx",
      "email": "Keven48@gmail.com"
    },
    {
      "id": 15,
      "username": "Vernie39",
      "password": "J1nwcCOGSoE_9Ro",
      "email": "Elliott52@yahoo.com"
    },
    {
      "id": 16,
      "username": "Omari28",
      "password": "H4mxHFb4Tj7jU_a",
      "email": "Addison_Beatty@yahoo.com"
    },
    {
      "id": 17,
      "username": "Mozelle.Effertz",
      "password": "8Udw7pjlgjFMIY1",
      "email": "Wyatt.Kohler@yahoo.com"
    },
    {
      "id": 18,
      "username": "Lisandro_Haag",
      "password": "TMCbr1GBRuFOkKT",
      "email": "Bethany70@gmail.com"
    },
    {
      "id": 19,
      "username": "Augustus64",
      "password": "h9FujGRGNWm1Lxq",
      "email": "Zoila_Mante@gmail.com"
    },
    {
      "id": 20,
      "username": "Laisha11",
      "password": "YJWww_FG4rEbI9D",
      "email": "Raegan.Mertz0@hotmail.com"
    },
    {
      "id": 21,
      "username": "Fermin.Conn",
      "password": "tMRlJOkl_wQJ5ZC",
      "email": "Magdalena.Reichel54@yahoo.com"
    },
    {
      "id": 22,
      "username": "Kailyn_Prosacco52",
      "password": "Ot_TOyEmraX4MYN",
      "email": "Darby10@yahoo.com"
    },
    {
      "id": 23,
      "username": "Erick.Reilly",
      "password": "y1OTPGVzYjhexje",
      "email": "Xavier52@hotmail.com"
    },
    {
      "id": 24,
      "username": "Gerry_Stroman65",
      "password": "_zZqUOuk1IyxZuk",
      "email": "Rubie99@hotmail.com"
    },
    {
      "id": 25,
      "username": "Americo.Crooks",
      "password": "e2nT9I55eiNU11H",
      "email": "Estella90@yahoo.com"
    },
    {
      "id": 26,
      "username": "Haleigh.Gorczany98",
      "password": "Z8rwlM1UTaz4Tyv",
      "email": "Stephen_Fadel@yahoo.com"
    },
    {
      "id": 27,
      "username": "Avery_DuBuque86",
      "password": "Xp7OK_Wt0BVNRKT",
      "email": "Nathen.Padberg43@gmail.com"
    },
    {
      "id": 28,
      "username": "Adelle87",
      "password": "unY91cYwYYk6tAz",
      "email": "Sally.Kunze@yahoo.com"
    },
    {
      "id": 29,
      "username": "Leora99",
      "password": "hPkkpxyiipu32Oo",
      "email": "Nestor.OConner33@hotmail.com"
    },
    {
      "id": 30,
      "username": "Oswald.Reynolds",
      "password": "6X65Mch8Eg7fYZW",
      "email": "Emmanuelle79@gmail.com"
    },
    {
      "id": 31,
      "username": "Jessika45",
      "password": "p6tvp8Wk5P_L8GV",
      "email": "Danial.Hane88@yahoo.com"
    },
    {
      "id": 32,
      "username": "Gust.Cummings",
      "password": "Vpx3E0YEBmSsYrg",
      "email": "Nikita.Corwin@gmail.com"
    },
    {
      "id": 33,
      "username": "Arden_Blick27",
      "password": "mJewmgIo6DzwxMr",
      "email": "Brigitte89@gmail.com"
    },
    {
      "id": 34,
      "username": "Oswaldo73",
      "password": "STd9Li_Lvy_gFBR",
      "email": "Ronaldo30@yahoo.com"
    },
    {
      "id": 35,
      "username": "Polly_Huel",
      "password": "7lV9NXFTkACXSsK",
      "email": "King_Lueilwitz@gmail.com"
    },
    {
      "id": 36,
      "username": "Mikayla52",
      "password": "wwwWydV1hEotnjW",
      "email": "Lambert2@gmail.com"
    },
    {
      "id": 37,
      "username": "Kennith.Windler",
      "password": "iryHZrnOF1e8Q7b",
      "email": "Ebony_Little98@hotmail.com"
    },
    {
      "id": 38,
      "username": "Forest_Langosh",
      "password": "MEvN2qDsUqHHqi7",
      "email": "Maci0@hotmail.com"
    },
    {
      "id": 39,
      "username": "Neha5",
      "password": "EIr7hevpfeg06ET",
      "email": "Carrie_Bashirian@gmail.com"
    },
    {
      "id": 40,
      "username": "Tyson_Koch",
      "password": "lHZ6g8nux6BnJVY",
      "email": "Jaylon.Huels17@hotmail.com"
    },
    {
      "id": 41,
      "username": "Cassandre.Schimmel68",
      "password": "CI_7SkSvSYCRuC6",
      "email": "Aiden.Gorczany20@yahoo.com"
    },
    {
      "id": 42,
      "username": "Steve.Davis",
      "password": "jqQg2dMK2JtQh81",
      "email": "Casimir.Zieme@yahoo.com"
    },
    {
      "id": 43,
      "username": "Rickey_Weissnat",
      "password": "GfEZsaGYc9kZOQk",
      "email": "Velma.Bashirian@hotmail.com"
    },
    {
      "id": 44,
      "username": "Vena_Cronin44",
      "password": "PuX58ZeIiAbhze7",
      "email": "Jaden_Kreiger@gmail.com"
    },
    {
      "id": 45,
      "username": "Melyssa.Sanford21",
      "password": "dmzsOehYmvSEgCI",
      "email": "Domenick.Funk52@hotmail.com"
    },
    {
      "id": 46,
      "username": "Lavina27",
      "password": "EkI3cch5GAW71cY",
      "email": "Santiago57@gmail.com"
    },
    {
      "id": 47,
      "username": "Allison.Little8",
      "password": "k4cxR21rl4IxVKN",
      "email": "Adam_Gerlach@yahoo.com"
    },
    {
      "id": 48,
      "username": "Christelle.Rodriguez",
      "password": "zoVwiIRTz9ZcKdo",
      "email": "Lawson.Stoltenberg@yahoo.com"
    },
    {
      "id": 49,
      "username": "Dulce32",
      "password": "joaMQZWtDaNKsnR",
      "email": "Carissa.Grady@gmail.com"
    },
    {
      "id": 50,
      "username": "Carmen_Huel23",
      "password": "DDCuOQ7NYM8ws3k",
      "email": "Lewis.Wolff49@gmail.com"
    },
    {
      "id": 51,
      "username": "Carrie.Lynch51",
      "password": "yKaYuiORD7lINI_",
      "email": "Georgette97@gmail.com"
    },
    {
      "id": 52,
      "username": "Maude.Dietrich75",
      "password": "yPbyE1Sv134P7Du",
      "email": "Wilma95@hotmail.com"
    },
    {
      "id": 53,
      "username": "Tianna.Douglas",
      "password": "KvMmmhcy6QgYZm7",
      "email": "Harley.Kuvalis42@hotmail.com"
    },
    {
      "id": 54,
      "username": "Sydni.McLaughlin",
      "password": "5T37nsoDDHVqG2R",
      "email": "Leann_Batz27@hotmail.com"
    },
    {
      "id": 55,
      "username": "Victoria.Ryan44",
      "password": "yu9gEdiemkHxKl0",
      "email": "Hal_Wilkinson38@yahoo.com"
    },
    {
      "id": 56,
      "username": "Meghan_Keeling89",
      "password": "5Az9S8t3srFnQPe",
      "email": "Kailyn5@hotmail.com"
    },
    {
      "id": 57,
      "username": "Carolyn.Johnson68",
      "password": "pzauJUEJONmULrM",
      "email": "Maudie.Kub96@hotmail.com"
    },
    {
      "id": 58,
      "username": "Jessie_Kilback25",
      "password": "BG7Hi42cGVZ5PXW",
      "email": "Clemmie_Kirlin64@gmail.com"
    },
    {
      "id": 59,
      "username": "Maureen.Jakubowski1",
      "password": "oCQGVnRy3pOmmh4",
      "email": "Sebastian21@yahoo.com"
    },
    {
      "id": 60,
      "username": "Jaida0",
      "password": "284eJlOr50FbGVY",
      "email": "Hettie_Schmeler@hotmail.com"
    },
    {
      "id": 61,
      "username": "Eileen.Harvey",
      "password": "6LfoxFh9x0xC9CI",
      "email": "Yoshiko_Dibbert@gmail.com"
    },
    {
      "id": 62,
      "username": "Elvera_Schaefer",
      "password": "kF1lskc0wLmQdUw",
      "email": "Brayan41@hotmail.com"
    },
    {
      "id": 63,
      "username": "Mathew.Schumm",
      "password": "VmWLe1QhllCJbPM",
      "email": "Seth_Witting@gmail.com"
    },
    {
      "id": 64,
      "username": "Emile90",
      "password": "yqHvu4dFTRQJT9q",
      "email": "Moriah58@hotmail.com"
    },
    {
      "id": 65,
      "username": "Jacklyn_OConner",
      "password": "JgVfJ7m0jxmKf2B",
      "email": "Jeromy77@hotmail.com"
    },
    {
      "id": 66,
      "username": "Glennie76",
      "password": "A6X0YZ7zPcwjaST",
      "email": "Marianna.Cormier@hotmail.com"
    },
    {
      "id": 67,
      "username": "Karl_Lemke",
      "password": "VAuQfzZcT1pdhca",
      "email": "Jayce_Macejkovic@yahoo.com"
    },
    {
      "id": 68,
      "username": "Paul_Jacobson29",
      "password": "yFZXffm82myDr2q",
      "email": "Irwin_Murazik@hotmail.com"
    },
    {
      "id": 69,
      "username": "Valentine15",
      "password": "6HGxfaOKcanVgLz",
      "email": "Humberto93@yahoo.com"
    },
    {
      "id": 70,
      "username": "Clair98",
      "password": "9NQ5gvNvSSoOJfp",
      "email": "Destin.Hodkiewicz80@gmail.com"
    },
    {
      "id": 71,
      "username": "Kenyon_Rohan18",
      "password": "9rWrALPMaD8zQ4f",
      "email": "Addison.Kreiger25@yahoo.com"
    },
    {
      "id": 72,
      "username": "Darrel.Hegmann47",
      "password": "zp_oMfAd38gYUjE",
      "email": "Alan11@yahoo.com"
    },
    {
      "id": 73,
      "username": "Odessa_Tromp50",
      "password": "dRxI5DOXDTGvhc9",
      "email": "Margarette_Orn54@gmail.com"
    },
    {
      "id": 74,
      "username": "Anthony13",
      "password": "q9aXF26kRq71Nmf",
      "email": "Ciara_Murray25@hotmail.com"
    },
    {
      "id": 75,
      "username": "Ashley_Homenick55",
      "password": "fBFxunJLjH3PkSL",
      "email": "Nannie_Dicki96@hotmail.com"
    },
    {
      "id": 76,
      "username": "Karianne83",
      "password": "M_HHg3ryK70HOuE",
      "email": "Eula_Morar84@hotmail.com"
    },
    {
      "id": 77,
      "username": "Wilford_Conn",
      "password": "OXMrsk0MHCoVzTc",
      "email": "Celestino_Wisoky@gmail.com"
    },
    {
      "id": 78,
      "username": "Blair35",
      "password": "hblPuzLXhEQJkZq",
      "email": "Adell_Morissette@yahoo.com"
    },
    {
      "id": 79,
      "username": "Cicero_Flatley",
      "password": "yxvCzGDBSfGuzs0",
      "email": "Madeline_Stehr16@yahoo.com"
    },
    {
      "id": 80,
      "username": "Anibal.Ritchie17",
      "password": "xht1qCRWBIwuSmQ",
      "email": "Maryam29@yahoo.com"
    },
    {
      "id": 81,
      "username": "Stephan10",
      "password": "hfU2fvIUsd63kFY",
      "email": "August_Reinger70@hotmail.com"
    },
    {
      "id": 82,
      "username": "Lou_Hansen31",
      "password": "LCoQIV3JIut9nRd",
      "email": "Kyler_Marvin@gmail.com"
    },
    {
      "id": 83,
      "username": "Leila.OConnell",
      "password": "znoDNi9fHbS8F08",
      "email": "Augustus75@gmail.com"
    },
    {
      "id": 84,
      "username": "Triston88",
      "password": "F88iduOXFJKSHwT",
      "email": "Bell5@hotmail.com"
    },
    {
      "id": 85,
      "username": "Bo_Donnelly45",
      "password": "Oa4QEDCklv9DLUP",
      "email": "Sarah_Considine36@yahoo.com"
    },
    {
      "id": 86,
      "username": "Myrtle_Keeling",
      "password": "SKR3v4vWA6SPNCX",
      "email": "Henri.Beier@yahoo.com"
    },
    {
      "id": 87,
      "username": "Josephine62",
      "password": "f8INss08n1F3mF9",
      "email": "Leonard58@yahoo.com"
    },
    {
      "id": 88,
      "username": "Tracey5",
      "password": "LlV3E7P6Q_Fmql0",
      "email": "Jerad30@yahoo.com"
    },
    {
      "id": 89,
      "username": "Myrl.Heidenreich28",
      "password": "15ALaswwKgbRO_R",
      "email": "Lamont81@hotmail.com"
    },
    {
      "id": 90,
      "username": "Veda.Mosciski",
      "password": "ooM89U_lko7KV3G",
      "email": "Jamison35@gmail.com"
    },
    {
      "id": 91,
      "username": "Richard.OHara95",
      "password": "Ya0dOy0Sg5mO7iM",
      "email": "Lenna_Gusikowski@hotmail.com"
    },
    {
      "id": 92,
      "username": "Miller.Labadie60",
      "password": "EWajx6x7DahrIhR",
      "email": "Dean_Bernhard@gmail.com"
    },
    {
      "id": 93,
      "username": "Letitia.Schaden",
      "password": "lQJRMj4uUaE1YF9",
      "email": "Dario_Klocko86@yahoo.com"
    },
    {
      "id": 94,
      "username": "Nicholas_Altenwerth",
      "password": "C5Ntax6Bng2kyT7",
      "email": "Blanca_Ziemann@gmail.com"
    },
    {
      "id": 95,
      "username": "Gabriel_Bashirian63",
      "password": "ijAtZmo_G618C6c",
      "email": "Robb.Bednar8@hotmail.com"
    },
    {
      "id": 96,
      "username": "Madaline99",
      "password": "4x4wr27tltqDjWr",
      "email": "Carrie.Jacobson76@hotmail.com"
    },
    {
      "id": 97,
      "username": "Delaney15",
      "password": "RKPKHteyt4SFNtp",
      "email": "Briana13@hotmail.com"
    },
    {
      "id": 98,
      "username": "Gabrielle19",
      "password": "TxiOLSgDaS962KV",
      "email": "Olin49@hotmail.com"
    },
    {
      "id": 99,
      "username": "Cortney71",
      "password": "emIu2G_SA3GBlPc",
      "email": "Minnie.White3@gmail.com"
    },
    {
      "id": 100,
      "username": "Araceli.Cruickshank",
      "password": "4VgjVnUAbW59Xvb",
      "email": "Antonietta35@gmail.com"
    },
    {
      "id": 101,
      "username": "Angelina.Adams76",
      "password": "2tCtVtBuiYGKKL7",
      "email": "Duane76@gmail.com"
    },
    {
      "id": 102,
      "username": "Ike31",
      "password": "TKlqNzrpSRd6xtK",
      "email": "Krystel97@hotmail.com"
    },
    {
      "id": 103,
      "username": "Everardo.Lang84",
      "password": "kaLDF9VjxVyqx_x",
      "email": "Rhiannon74@hotmail.com"
    },
    {
      "id": 104,
      "username": "Ivy23",
      "password": "yo0xvCIeeviWQzN",
      "email": "Dashawn_Bergstrom64@yahoo.com"
    },
    {
      "id": 105,
      "username": "Hertha_Walsh",
      "password": "ySC2sXjKP1kaFx5",
      "email": "Rodrigo51@gmail.com"
    },
    {
      "id": 106,
      "username": "Annabelle6",
      "password": "y0AYHVkwnCZiDaj",
      "email": "Guido_Walsh58@yahoo.com"
    },
    {
      "id": 107,
      "username": "Kyle_Trantow82",
      "password": "f3VOESfl8HvZgZ5",
      "email": "Candice.Sipes86@yahoo.com"
    },
    {
      "id": 108,
      "username": "Jeff_Hilpert53",
      "password": "jg3hr8y4WNnmQKf",
      "email": "Cleora76@gmail.com"
    },
    {
      "id": 109,
      "username": "Scotty16",
      "password": "Rgee7mrBkb8Ltgi",
      "email": "Madelyn0@gmail.com"
    },
    {
      "id": 110,
      "username": "Calista61",
      "password": "IwQRDUziTILJm1R",
      "email": "Napoleon.Block@yahoo.com"
    },
    {
      "id": 111,
      "username": "Georgiana.Hartmann86",
      "password": "euIPtl5ly2x6E9N",
      "email": "Gregory_Koepp@hotmail.com"
    },
    {
      "id": 112,
      "username": "Hellen.Macejkovic5",
      "password": "74t2q3m8Ts1P9mF",
      "email": "Eldon.Kuhn@gmail.com"
    },
    {
      "id": 113,
      "username": "Elaina30",
      "password": "Pls_ocz3EXnYuNh",
      "email": "Frida.Rolfson32@yahoo.com"
    },
    {
      "id": 114,
      "username": "Reggie_Frami",
      "password": "jbfLJM1PknnRGGR",
      "email": "Nelda20@hotmail.com"
    },
    {
      "id": 115,
      "username": "Santiago_Schultz",
      "password": "mfn5kFUPlnY8N5e",
      "email": "Cory74@yahoo.com"
    },
    {
      "id": 116,
      "username": "Neva.Schamberger37",
      "password": "dSeJLJDwtkIngIr",
      "email": "Herta_Mueller67@hotmail.com"
    },
    {
      "id": 117,
      "username": "Wilton90",
      "password": "Oc7VCATLOyMDcQo",
      "email": "Brandt_Collins76@yahoo.com"
    },
    {
      "id": 118,
      "username": "Albertha.Strosin",
      "password": "2XXApUu4zvpdpmG",
      "email": "Stevie.Blick@hotmail.com"
    },
    {
      "id": 119,
      "username": "Phoebe30",
      "password": "nLGYeWmh07cRUIh",
      "email": "Werner_Gibson70@gmail.com"
    },
    {
      "id": 120,
      "username": "Jon9",
      "password": "mM7oBzFmogC5UWE",
      "email": "Jennie83@hotmail.com"
    },
    {
      "id": 121,
      "username": "Javonte_Keeling",
      "password": "2ZAJYlxqgfCWph1",
      "email": "Zola_Langworth@gmail.com"
    },
    {
      "id": 122,
      "username": "Curtis_Langworth98",
      "password": "Iown6uPcia6auja",
      "email": "Michaela_OReilly@hotmail.com"
    },
    {
      "id": 123,
      "username": "Treva.Friesen",
      "password": "JCqF3o1udMyZm2A",
      "email": "Gloria28@gmail.com"
    },
    {
      "id": 124,
      "username": "Hunter.Gulgowski",
      "password": "9Iq7GXA5S81lwaF",
      "email": "Vickie_Jakubowski67@yahoo.com"
    },
    {
      "id": 125,
      "username": "King27",
      "password": "0Unb7Ye5TI5uxxz",
      "email": "Cordell.Bechtelar@yahoo.com"
    },
    {
      "id": 126,
      "username": "Anjali.Cremin25",
      "password": "lSPBDpphV61hW02",
      "email": "Serenity29@yahoo.com"
    },
    {
      "id": 127,
      "username": "Antonetta_Abshire",
      "password": "a_MqGX_0SkvfO1T",
      "email": "Jocelyn.Davis@hotmail.com"
    },
    {
      "id": 128,
      "username": "Adella.Rogahn83",
      "password": "J3xEmqmg1ToiCCH",
      "email": "Elsa_Bernhard@gmail.com"
    },
    {
      "id": 129,
      "username": "Jayme_Hettinger",
      "password": "dkS2YpiOcozcec5",
      "email": "Drake21@gmail.com"
    },
    {
      "id": 130,
      "username": "Nova38",
      "password": "pRU7PNexEQXEtgY",
      "email": "Maxine_Walker70@yahoo.com"
    },
    {
      "id": 131,
      "username": "Heidi.Rosenbaum",
      "password": "Bx4M46MvoPUtHiq",
      "email": "Dorcas.Prosacco49@hotmail.com"
    },
    {
      "id": 132,
      "username": "Heath42",
      "password": "mN87IJKkrI7eyx2",
      "email": "Eduardo_Bayer@hotmail.com"
    },
    {
      "id": 133,
      "username": "Willy_Blick",
      "password": "JjAjDvXYwgaEYt_",
      "email": "Hyman55@yahoo.com"
    },
    {
      "id": 134,
      "username": "Braxton_Gleason",
      "password": "QCqIwfgVmxROilP",
      "email": "Stevie20@hotmail.com"
    },
    {
      "id": 135,
      "username": "Magali4",
      "password": "_prfie5JBrGfqvC",
      "email": "Lois_Fay71@hotmail.com"
    },
    {
      "id": 136,
      "username": "Tate88",
      "password": "HsFIhrajgo1nkUh",
      "email": "Edward_Goodwin@hotmail.com"
    },
    {
      "id": 137,
      "username": "Russ_Dach",
      "password": "5ZVqIbDRXUZcwgG",
      "email": "Darien_Goodwin37@yahoo.com"
    },
    {
      "id": 138,
      "username": "Eleanora_Gerhold",
      "password": "TS3Rfru8dmXUehT",
      "email": "Antone79@yahoo.com"
    },
    {
      "id": 139,
      "username": "Domingo.Grady18",
      "password": "q9jqw_aF5nkRECc",
      "email": "Al87@gmail.com"
    },
    {
      "id": 140,
      "username": "Ladarius.Shields93",
      "password": "bknNP7sdGuoP65n",
      "email": "Jennyfer30@yahoo.com"
    },
    {
      "id": 141,
      "username": "Branson14",
      "password": "xJ0Q6i39GDgkD1M",
      "email": "Nigel1@yahoo.com"
    },
    {
      "id": 142,
      "username": "Miguel.Senger",
      "password": "jY1L_cJCObhjQT6",
      "email": "Salvatore58@hotmail.com"
    },
    {
      "id": 143,
      "username": "Clement.OKon",
      "password": "jI3kSbfEmunZyu5",
      "email": "Bell.Howell83@gmail.com"
    },
    {
      "id": 144,
      "username": "Jean.Kertzmann",
      "password": "GJ6K74WVHlzjHmO",
      "email": "Natasha.Stroman@yahoo.com"
    },
    {
      "id": 145,
      "username": "Garret.Kris",
      "password": "64lgWunjuglVpkS",
      "email": "Kylie87@hotmail.com"
    },
    {
      "id": 146,
      "username": "Lyla.Quigley35",
      "password": "pY3uoPbYB4vlR1V",
      "email": "Shanny.Lemke92@gmail.com"
    },
    {
      "id": 147,
      "username": "Chelsea97",
      "password": "CrvLV7wcWaMtQT8",
      "email": "Monserrate_Armstrong@yahoo.com"
    },
    {
      "id": 148,
      "username": "Eleanora_Adams",
      "password": "8oO6ePRhO9kX73W",
      "email": "Hazel.Reinger74@yahoo.com"
    },
    {
      "id": 149,
      "username": "Lexi_Dicki",
      "password": "yNJcMjRk6vtLxPd",
      "email": "Nellie.Johnston53@hotmail.com"
    },
    {
      "id": 150,
      "username": "Trudie.Wilkinson",
      "password": "_lKkb4x1H9pds7q",
      "email": "Karelle.Langosh@hotmail.com"
    },
    {
      "id": 151,
      "username": "Ramiro_Ondricka78",
      "password": "CX2GlWHOrdvM9gn",
      "email": "Laury.Fisher31@hotmail.com"
    },
    {
      "id": 152,
      "username": "Lon96",
      "password": "6kOAonO9zJYr8gF",
      "email": "Erick.Morar@yahoo.com"
    },
    {
      "id": 153,
      "username": "Brigitte.Grady40",
      "password": "xOsPUMi6ArmPy22",
      "email": "Carlo_Bruen@hotmail.com"
    },
    {
      "id": 154,
      "username": "Demario_Parker44",
      "password": "aGWXsMMvfbrM68E",
      "email": "Bobbie.Ziemann94@hotmail.com"
    },
    {
      "id": 155,
      "username": "Madisyn.Goyette72",
      "password": "Gw9HlYwWdx0em4j",
      "email": "Sheridan.Zboncak83@yahoo.com"
    },
    {
      "id": 156,
      "username": "Dejuan5",
      "password": "QL6gKP5VxhXPVd1",
      "email": "Cody8@hotmail.com"
    },
    {
      "id": 157,
      "username": "Clement.Ernser98",
      "password": "1CLkL6sowcPq2ha",
      "email": "Cody23@yahoo.com"
    },
    {
      "id": 158,
      "username": "Jacquelyn10",
      "password": "2nfNhJj9tq98cKk",
      "email": "Alysa78@hotmail.com"
    },
    {
      "id": 159,
      "username": "Rogers.Marvin1",
      "password": "8VgQT17CyoeFQw8",
      "email": "Henry74@yahoo.com"
    },
    {
      "id": 160,
      "username": "Arnaldo97",
      "password": "vxfPmBDsKCXkAvj",
      "email": "Lurline_Wunsch2@yahoo.com"
    },
    {
      "id": 161,
      "username": "Chris_Armstrong91",
      "password": "crRSti72TVpzjZH",
      "email": "Tremayne80@gmail.com"
    },
    {
      "id": 162,
      "username": "Orion64",
      "password": "cwUnF4rSK8zdW_E",
      "email": "Mark35@hotmail.com"
    },
    {
      "id": 163,
      "username": "Rachel.Rolfson44",
      "password": "xLz1zXDmwqeBkJj",
      "email": "Cassandre_Hirthe@yahoo.com"
    },
    {
      "id": 164,
      "username": "Joshua.Boyle",
      "password": "zdazkuvqBVN2irH",
      "email": "Ansley89@hotmail.com"
    },
    {
      "id": 165,
      "username": "Amos.Adams12",
      "password": "n99XbukW9ShmJty",
      "email": "Leone_Wyman@gmail.com"
    },
    {
      "id": 166,
      "username": "Muhammad_Ebert85",
      "password": "IZzsI9aBUQVsF4Z",
      "email": "Talia_Kassulke@hotmail.com"
    },
    {
      "id": 167,
      "username": "Ryley_Ullrich",
      "password": "Xv5IaTHAfDLiCVH",
      "email": "Anya35@hotmail.com"
    },
    {
      "id": 168,
      "username": "Eunice_Cole31",
      "password": "4NfqbRp10aJUz9J",
      "email": "Axel.Heathcote@yahoo.com"
    },
    {
      "id": 169,
      "username": "Zita74",
      "password": "qOGKGcOlt4W6J6z",
      "email": "Finn9@hotmail.com"
    },
    {
      "id": 170,
      "username": "Alvis56",
      "password": "_wdO3NWH9AlrYRJ",
      "email": "Salvador.Bechtelar76@hotmail.com"
    },
    {
      "id": 171,
      "username": "Rene.Torp64",
      "password": "7Svppunl6DMU9c2",
      "email": "Dan_Howe95@hotmail.com"
    },
    {
      "id": 172,
      "username": "Narciso.Balistreri42",
      "password": "a_C24pgABHp4iHH",
      "email": "Bernadine_Abernathy@hotmail.com"
    },
    {
      "id": 173,
      "username": "Mckenzie.King",
      "password": "ez8QQQ8LgaLsEKc",
      "email": "Amiya_Stiedemann55@yahoo.com"
    },
    {
      "id": 174,
      "username": "Marley3",
      "password": "ticD4OrZ4VsfOih",
      "email": "Tyson_Collins19@yahoo.com"
    },
    {
      "id": 175,
      "username": "Lilyan.Renner53",
      "password": "qHXR9pflSIFX3tW",
      "email": "Lawrence_Durgan@hotmail.com"
    },
    {
      "id": 176,
      "username": "Tracey2",
      "password": "GRauqVwJ9pbIpIl",
      "email": "Sabryna95@yahoo.com"
    },
    {
      "id": 177,
      "username": "Robb40",
      "password": "ZgNkvxojw0m1PYu",
      "email": "Rod_Hagenes@gmail.com"
    },
    {
      "id": 178,
      "username": "Darwin_Boyer54",
      "password": "iiujJ3nQoffSIGD",
      "email": "Florencio88@gmail.com"
    },
    {
      "id": 179,
      "username": "Jessie_Kihn",
      "password": "5OmXmvv_SRGzxwa",
      "email": "Camren78@gmail.com"
    },
    {
      "id": 180,
      "username": "Sabryna.Durgan",
      "password": "gy_PStgz7tslmDJ",
      "email": "Emelia_Fadel@hotmail.com"
    },
    {
      "id": 181,
      "username": "Ronaldo40",
      "password": "_TdKJcrzSGgetly",
      "email": "Lenny48@yahoo.com"
    },
    {
      "id": 182,
      "username": "Anastasia_Armstrong",
      "password": "oBrVPwppWzNuziB",
      "email": "Camille.Franecki@hotmail.com"
    },
    {
      "id": 183,
      "username": "Jeremie.Cole",
      "password": "N_Ee7c3jjq2XXkX",
      "email": "Vivian4@yahoo.com"
    },
    {
      "id": 184,
      "username": "Celestino_Williamson41",
      "password": "e_EZIvGP3Hx8unq",
      "email": "Nya_Hoeger@gmail.com"
    },
    {
      "id": 185,
      "username": "Isidro.Olson63",
      "password": "q8e8Aw9rG8XPTsC",
      "email": "Finn_Spencer7@hotmail.com"
    },
    {
      "id": 186,
      "username": "Hadley.Mills33",
      "password": "ML2569MeoWDodqF",
      "email": "Dorian_Simonis@gmail.com"
    },
    {
      "id": 187,
      "username": "Madge_Kessler57",
      "password": "2MTzKpW0A8W3NGA",
      "email": "Ted_Runolfsdottir@gmail.com"
    },
    {
      "id": 188,
      "username": "Arvilla.McCullough",
      "password": "GGKKwWJIIb7XtB3",
      "email": "Noel.Beer94@gmail.com"
    },
    {
      "id": 189,
      "username": "Nakia.Hodkiewicz82",
      "password": "KSB7rIQwcyJH4fK",
      "email": "Madison_Lang@hotmail.com"
    },
    {
      "id": 190,
      "username": "Malcolm.Bernier35",
      "password": "gxRruSCMK7g4K7o",
      "email": "Eriberto_Leffler71@gmail.com"
    },
    {
      "id": 191,
      "username": "Bobby21",
      "password": "JvHm1nXHY5ZkY7Y",
      "email": "Caleb.Swift@hotmail.com"
    },
    {
      "id": 192,
      "username": "Ellie_Pacocha",
      "password": "feRPs1KKOcyibmI",
      "email": "Lysanne.Jacobi@yahoo.com"
    },
    {
      "id": 193,
      "username": "Pamela.Skiles82",
      "password": "VcKhKpqyjWe42PH",
      "email": "Alek.Gislason20@gmail.com"
    },
    {
      "id": 194,
      "username": "Mac21",
      "password": "fZ3sCTbjTv6SRBa",
      "email": "Princess_Terry@yahoo.com"
    },
    {
      "id": 195,
      "username": "Derek.Orn13",
      "password": "G6A3QUmoMPB2th7",
      "email": "Rahul_McCullough@gmail.com"
    },
    {
      "id": 196,
      "username": "Raina18",
      "password": "37sAB7nWTGLkqEl",
      "email": "Kristina.Yundt28@hotmail.com"
    },
    {
      "id": 197,
      "username": "Kristoffer_Waters71",
      "password": "asYE2tNVQMDBmHk",
      "email": "Mary6@gmail.com"
    },
    {
      "id": 198,
      "username": "Letha12",
      "password": "ma6WmFzs3euZkVp",
      "email": "Enoch_Spencer19@yahoo.com"
    },
    {
      "id": 199,
      "username": "Gerda61",
      "password": "SD74K4c1oOrycrz",
      "email": "Noemi_Ferry79@yahoo.com"
    },
    {
      "id": 200,
      "username": "Leland28",
      "password": "37Me6RauN84GVYD",
      "email": "Rupert0@gmail.com"
    }
  ],
  "contacts": [
    {
      "id": 1,
      "firstName": "Ahmed",
      "lastName": "Bouchefra",
      "email": "ahmed.bouchefra@gmail.com",
      "phone": "(387) 592-6773",
      "city": "Agadir",
      "country": "Morrocco",
      "title": "Developer"
    },
    {
      "id": 2,
      "firstName": "Luther",
      "lastName": "McLaughlin",
      "email": "Darlene_Mayert33@gmail.com",
      "phone": "091-637-1228 x75335",
      "city": "West Creola",
      "country": "Bahamas",
      "title": "Principal Implementation Supervisor"
    },
    {
      "id": 3,
      "firstName": "Ettie",
      "lastName": "VonRueden",
      "email": "Estrella.Emmerich@gmail.com",
      "phone": "(786) 638-5754 x250",
      "city": "Beahanhaven",
      "country": "Liberia",
      "title": "Chief Operations Assistant"
    },
    {
      "id": 4,
      "firstName": "Jamir",
      "lastName": "Satterfield",
      "email": "Violette.Morissette7@gmail.com",
      "phone": "1-209-432-0143",
      "city": "Lake Madalyn",
      "country": "Guinea",
      "title": "Corporate Intranet Analyst"
    },
    {
      "id": 5,
      "firstName": "Jacky",
      "lastName": "Macejkovic",
      "email": "Jermaine_Dickens@yahoo.com",
      "phone": "484.918.8102 x5226",
      "city": "Lake Myron",
      "country": "Tanzania",
      "title": "Future Group Technician"
    },
    {
      "id": 6,
      "firstName": "Nayeli",
      "lastName": "Thompson",
      "email": "Laura41@hotmail.com",
      "phone": "146.149.9957",
      "city": "South Hailee",
      "country": "Poland",
      "title": "Customer Marketing Assistant"
    },
    {
      "id": 7,
      "firstName": "Kaycee",
      "lastName": "Beer",
      "email": "Annamarie10@yahoo.com",
      "phone": "(416) 876-0688 x24935",
      "city": "Mellieshire",
      "country": "Suriname",
      "title": "Customer Accounts Representative"
    },
    {
      "id": 8,
      "firstName": "Jacklyn",
      "lastName": "McCullough",
      "email": "Velva_Corwin@gmail.com",
      "phone": "778-220-5862 x71043",
      "city": "Crystalmouth",
      "country": "Congo",
      "title": "Global Tactics Producer"
    },
    {
      "id": 9,
      "firstName": "Westley",
      "lastName": "DuBuque",
      "email": "Gerardo.Gerhold97@hotmail.com",
      "phone": "490.768.2387 x8559",
      "city": "New Curtport",
      "country": "Namibia",
      "title": "Future Response Coordinator"
    },
    {
      "id": 10,
      "firstName": "Reta",
      "lastName": "Ortiz",
      "email": "Zora.Rodriguez@hotmail.com",
      "phone": "1-293-117-3182 x235",
      "city": "New Bo",
      "country": "Svalbard & Jan Mayen Islands",
      "title": "Future Accounts Administrator"
    },
    {
      "id": 11,
      "firstName": "Roscoe",
      "lastName": "Treutel",
      "email": "Trudie_Lang@hotmail.com",
      "phone": "1-312-989-5810 x115",
      "city": "East Creola",
      "country": "United Arab Emirates",
      "title": "Direct Security Consultant"
    },
    {
      "id": 12,
      "firstName": "Clara",
      "lastName": "Kihn",
      "email": "Berenice95@yahoo.com",
      "phone": "456.440.1086 x66104",
      "city": "South Bessie",
      "country": "Iceland",
      "title": "Global Optimization Officer"
    },
    {
      "id": 13,
      "firstName": "Tyree",
      "lastName": "Jaskolski",
      "email": "Sigmund.Orn@yahoo.com",
      "phone": "395.669.3120 x29685",
      "city": "Hermantown",
      "country": "Libyan Arab Jamahiriya",
      "title": "Corporate Communications Technician"
    },
    {
      "id": 14,
      "firstName": "Kaylah",
      "lastName": "Zemlak",
      "email": "River_Gulgowski@yahoo.com",
      "phone": "907-131-8420 x22373",
      "city": "Brakuston",
      "country": "Antarctica (the territory South of 60 deg S)",
      "title": "National Accounts Coordinator"
    },
    {
      "id": 15,
      "firstName": "Demond",
      "lastName": "Adams",
      "email": "Abbey.Mertz@yahoo.com",
      "phone": "314-030-1118",
      "city": "Port Kentown",
      "country": "Guyana",
      "title": "National Group Director"
    },
    {
      "id": 16,
      "firstName": "Ross",
      "lastName": "Walsh",
      "email": "Nat_Koss72@gmail.com",
      "phone": "(497) 057-0575 x9007",
      "city": "Grovertown",
      "country": "Qatar",
      "title": "Principal Intranet Architect"
    },
    {
      "id": 17,
      "firstName": "Laverne",
      "lastName": "Cartwright",
      "email": "Brooklyn_Bosco19@hotmail.com",
      "phone": "1-277-308-8336 x983",
      "city": "East Demario",
      "country": "Palau",
      "title": "Customer Directives Agent"
    },
    {
      "id": 18,
      "firstName": "Olen",
      "lastName": "Walter",
      "email": "Jonatan80@gmail.com",
      "phone": "(991) 113-5919 x44037",
      "city": "Connstad",
      "country": "Tokelau",
      "title": "Central Interactions Representative"
    },
    {
      "id": 19,
      "firstName": "Emilie",
      "lastName": "Klein",
      "email": "Magdalena_Cassin28@gmail.com",
      "phone": "813-131-2808 x865",
      "city": "Port Eunastad",
      "country": "French Polynesia",
      "title": "Dynamic Data Agent"
    },
    {
      "id": 20,
      "firstName": "Dudley",
      "lastName": "Corwin",
      "email": "Lupe.Roob80@yahoo.com",
      "phone": "1-892-321-6471 x1927",
      "city": "East Destany",
      "country": "Brazil",
      "title": "Central Integration Executive"
    },
    {
      "id": 21,
      "firstName": "Ezra",
      "lastName": "Nicolas",
      "email": "Buford33@gmail.com",
      "phone": "1-099-711-4321",
      "city": "Port Margarette",
      "country": "India",
      "title": "Global Division Representative"
    },
    {
      "id": 22,
      "firstName": "Sienna",
      "lastName": "Dicki",
      "email": "Mathilde84@gmail.com",
      "phone": "(803) 114-1151 x248",
      "city": "Manuelaport",
      "country": "Russian Federation",
      "title": "Product Identity Planner"
    },
    {
      "id": 23,
      "firstName": "Opal",
      "lastName": "Homenick",
      "email": "Monica_Barton20@yahoo.com",
      "phone": "685.005.9360 x5712",
      "city": "South Victor",
      "country": "Jamaica",
      "title": "Central Functionality Technician"
    },
    {
      "id": 24,
      "firstName": "Vallie",
      "lastName": "Heidenreich",
      "email": "Kianna60@yahoo.com",
      "phone": "610.559.9157 x10597",
      "city": "Jailynmouth",
      "country": "Vietnam",
      "title": "Regional Functionality Agent"
    },
    {
      "id": 25,
      "firstName": "Jackeline",
      "lastName": "Kshlerin",
      "email": "Diamond83@yahoo.com",
      "phone": "1-133-043-7157 x65198",
      "city": "Neomaview",
      "country": "Libyan Arab Jamahiriya",
      "title": "Lead Mobility Representative"
    },
    {
      "id": 26,
      "firstName": "Robert",
      "lastName": "Thompson",
      "email": "Emmie_Schmitt87@hotmail.com",
      "phone": "(861) 963-5767 x6922",
      "city": "Priceton",
      "country": "Gibraltar",
      "title": "Legacy Implementation Director"
    },
    {
      "id": 27,
      "firstName": "Ruth",
      "lastName": "MacGyver",
      "email": "Larry32@yahoo.com",
      "phone": "1-027-929-6670 x454",
      "city": "South Geovany",
      "country": "Mayotte",
      "title": "Senior Metrics Planner"
    },
    {
      "id": 28,
      "firstName": "Annabel",
      "lastName": "Kunze",
      "email": "Gwen.Sipes@yahoo.com",
      "phone": "744.084.2602",
      "city": "Port Johnpaul",
      "country": "Congo",
      "title": "Central Factors Liaison"
    },
    {
      "id": 29,
      "firstName": "Alene",
      "lastName": "Wunsch",
      "email": "Corene.Jacobi@gmail.com",
      "phone": "(771) 834-8197 x763",
      "city": "Emardland",
      "country": "Bolivia",
      "title": "Chief Web Officer"
    },
    {
      "id": 30,
      "firstName": "Tierra",
      "lastName": "Hills",
      "email": "Romaine34@gmail.com",
      "phone": "813.511.7213",
      "city": "Lake Deshawn",
      "country": "United States of America",
      "title": "Customer Configuration Assistant"
    },
    {
      "id": 31,
      "firstName": "Liliane",
      "lastName": "Deckow",
      "email": "Alene.Donnelly21@gmail.com",
      "phone": "433-436-3699 x49408",
      "city": "Kundeport",
      "country": "Oman",
      "title": "Principal Security Technician"
    },
    {
      "id": 32,
      "firstName": "Maynard",
      "lastName": "Rau",
      "email": "Shad.Emmerich4@yahoo.com",
      "phone": "(427) 588-0153",
      "city": "Port Lorenza",
      "country": "Barbados",
      "title": "Lead Functionality Assistant"
    },
    {
      "id": 33,
      "firstName": "Gaetano",
      "lastName": "Hyatt",
      "email": "Angeline.Abshire@yahoo.com",
      "phone": "876.233.6539",
      "city": "South Berniece",
      "country": "Burundi",
      "title": "Central Data Analyst"
    },
    {
      "id": 34,
      "firstName": "Axel",
      "lastName": "Buckridge",
      "email": "Pat_Renner93@yahoo.com",
      "phone": "1-907-748-4518 x74752",
      "city": "North Keanuborough",
      "country": "Costa Rica",
      "title": "Lead Functionality Orchestrator"
    },
    {
      "id": 35,
      "firstName": "Melvin",
      "lastName": "Paucek",
      "email": "Ludie71@yahoo.com",
      "phone": "1-014-574-0095",
      "city": "Markusfort",
      "country": "Denmark",
      "title": "Internal Optimization Designer"
    },
    {
      "id": 36,
      "firstName": "Jessika",
      "lastName": "Barton",
      "email": "Gerry_Ullrich39@yahoo.com",
      "phone": "1-295-530-1821 x340",
      "city": "Lake Jerryhaven",
      "country": "Belize",
      "title": "Forward Tactics Liaison"
    },
    {
      "id": 37,
      "firstName": "Maurine",
      "lastName": "Langosh",
      "email": "Jakayla_Treutel15@gmail.com",
      "phone": "1-594-790-4112 x98732",
      "city": "Port Lilianmouth",
      "country": "Lesotho",
      "title": "Senior Branding Director"
    },
    {
      "id": 38,
      "firstName": "Gerhard",
      "lastName": "Block",
      "email": "Gene.Wolf@yahoo.com",
      "phone": "512.970.8724 x9826",
      "city": "North Trycia",
      "country": "Portugal",
      "title": "Lead Response Producer"
    },
    {
      "id": 39,
      "firstName": "Brandy",
      "lastName": "Upton",
      "email": "Juwan_Sipes@gmail.com",
      "phone": "(196) 716-4463 x140",
      "city": "South Ludwig",
      "country": "Ireland",
      "title": "Dynamic Functionality Director"
    },
    {
      "id": 40,
      "firstName": "Henriette",
      "lastName": "Johns",
      "email": "Parker.Padberg@gmail.com",
      "phone": "340.632.8229",
      "city": "East Dahliachester",
      "country": "Haiti",
      "title": "International Intranet Assistant"
    },
    {
      "id": 41,
      "firstName": "Raphael",
      "lastName": "Johnston",
      "email": "Therese_Cronin@gmail.com",
      "phone": "(264) 936-3657",
      "city": "Wolfburgh",
      "country": "Senegal",
      "title": "Product Security Developer"
    },
    {
      "id": 42,
      "firstName": "Beaulah",
      "lastName": "Von",
      "email": "Emmet.Stroman@gmail.com",
      "phone": "655-954-6897",
      "city": "Zboncakhaven",
      "country": "Netherlands",
      "title": "National Security Supervisor"
    },
    {
      "id": 43,
      "firstName": "Hollis",
      "lastName": "Price",
      "email": "Leonor94@hotmail.com",
      "phone": "446-899-0240 x6042",
      "city": "South Jerodburgh",
      "country": "Togo",
      "title": "Global Accounts Executive"
    },
    {
      "id": 44,
      "firstName": "Chanelle",
      "lastName": "Turcotte",
      "email": "Harmony96@gmail.com",
      "phone": "464.003.0337 x550",
      "city": "Sanfordstad",
      "country": "Moldova",
      "title": "Dynamic Interactions Consultant"
    },
    {
      "id": 45,
      "firstName": "Rogers",
      "lastName": "Gutkowski",
      "email": "Rusty.Kling@yahoo.com",
      "phone": "(977) 778-6158",
      "city": "Lake Hobartfurt",
      "country": "Netherlands Antilles",
      "title": "Investor Directives Executive"
    },
    {
      "id": 46,
      "firstName": "Marshall",
      "lastName": "Kiehn",
      "email": "Brionna.Steuber0@gmail.com",
      "phone": "1-825-740-1009 x188",
      "city": "Lake Nola",
      "country": "Cook Islands",
      "title": "Product Infrastructure Producer"
    },
    {
      "id": 47,
      "firstName": "Kallie",
      "lastName": "Tremblay",
      "email": "Jaiden_Hagenes@hotmail.com",
      "phone": "1-235-911-5858 x2090",
      "city": "Wildermanville",
      "country": "Cameroon",
      "title": "Human Configuration Planner"
    },
    {
      "id": 48,
      "firstName": "Ignacio",
      "lastName": "Beatty",
      "email": "Hershel.Dare@hotmail.com",
      "phone": "625.990.2802 x58690",
      "city": "East Alden",
      "country": "Argentina",
      "title": "District Assurance Planner"
    },
    {
      "id": 49,
      "firstName": "Damien",
      "lastName": "Halvorson",
      "email": "Rusty82@yahoo.com",
      "phone": "496-179-3234",
      "city": "Hesterfort",
      "country": "Canada",
      "title": "Forward Metrics Supervisor"
    },
    {
      "id": 50,
      "firstName": "Raymundo",
      "lastName": "Jerde",
      "email": "Cyril.Weber@gmail.com",
      "phone": "1-362-408-5433",
      "city": "West Bertrand",
      "country": "Moldova",
      "title": "Senior Response Strategist"
    },
    {
      "id": 51,
      "firstName": "Kenya",
      "lastName": "Koss",
      "email": "Randall_Hane99@hotmail.com",
      "phone": "1-926-439-5399",
      "city": "Nicolaston",
      "country": "Indonesia",
      "title": "Human Security Analyst"
    },
    {
      "id": 52,
      "firstName": "Carroll",
      "lastName": "Gleichner",
      "email": "Claudie76@yahoo.com",
      "phone": "1-288-769-9198 x027",
      "city": "South Duane",
      "country": "Jordan",
      "title": "Investor Web Administrator"
    },
    {
      "id": 53,
      "firstName": "Rosalinda",
      "lastName": "Carter",
      "email": "Sanford_Walker69@gmail.com",
      "phone": "1-864-098-0624",
      "city": "Boganborough",
      "country": "Togo",
      "title": "Principal Markets Facilitator"
    },
    {
      "id": 54,
      "firstName": "Elyssa",
      "lastName": "Shanahan",
      "email": "David86@hotmail.com",
      "phone": "686-066-8327 x09109",
      "city": "Rosalindachester",
      "country": "Georgia",
      "title": "Future Security Associate"
    },
    {
      "id": 55,
      "firstName": "Lilyan",
      "lastName": "Altenwerth",
      "email": "Moses70@hotmail.com",
      "phone": "061-860-2221",
      "city": "South Zellaton",
      "country": "San Marino",
      "title": "Dynamic Group Officer"
    },
    {
      "id": 56,
      "firstName": "Dina",
      "lastName": "Sipes",
      "email": "Aracely.Gerhold33@yahoo.com",
      "phone": "1-748-811-7636 x94084",
      "city": "Trevorhaven",
      "country": "Cote d'Ivoire",
      "title": "International Operations Strategist"
    },
    {
      "id": 57,
      "firstName": "Lilliana",
      "lastName": "Quitzon",
      "email": "Taryn35@gmail.com",
      "phone": "121-965-3125 x15720",
      "city": "South Hannahview",
      "country": "Bahrain",
      "title": "Future Web Engineer"
    },
    {
      "id": 58,
      "firstName": "Joey",
      "lastName": "Mitchell",
      "email": "Alexys34@yahoo.com",
      "phone": "017-160-7354 x20216",
      "city": "MacGyverport",
      "country": "Gambia",
      "title": "Dynamic Implementation Director"
    },
    {
      "id": 59,
      "firstName": "Koby",
      "lastName": "Wisozk",
      "email": "Elody39@yahoo.com",
      "phone": "(129) 447-1610 x723",
      "city": "Port Chyna",
      "country": "Guam",
      "title": "Principal Data Manager"
    },
    {
      "id": 60,
      "firstName": "Mariam",
      "lastName": "Greenfelder",
      "email": "Loraine.Murazik78@hotmail.com",
      "phone": "242-678-1473 x6601",
      "city": "Lake Celine",
      "country": "Somalia",
      "title": "Central Applications Officer"
    },
    {
      "id": 61,
      "firstName": "Sigurd",
      "lastName": "Treutel",
      "email": "Pattie.Gutkowski71@yahoo.com",
      "phone": "(438) 508-4499",
      "city": "Enricoburgh",
      "country": "Kiribati",
      "title": "Central Markets Administrator"
    },
    {
      "id": 62,
      "firstName": "Katlyn",
      "lastName": "Daniel",
      "email": "Cayla_Kuhn@hotmail.com",
      "phone": "(012) 112-3371 x90263",
      "city": "Aprilhaven",
      "country": "Saint Lucia",
      "title": "Customer Accountability Liaison"
    },
    {
      "id": 63,
      "firstName": "Elton",
      "lastName": "Bartell",
      "email": "Charlie66@yahoo.com",
      "phone": "(541) 430-2570 x7575",
      "city": "East Noemi",
      "country": "Guernsey",
      "title": "Direct Functionality Architect"
    },
    {
      "id": 64,
      "firstName": "Eldon",
      "lastName": "Cronin",
      "email": "Marques78@hotmail.com",
      "phone": "488.786.9990 x81958",
      "city": "New Marlene",
      "country": "Austria",
      "title": "Product Group Supervisor"
    },
    {
      "id": 65,
      "firstName": "Layla",
      "lastName": "Kuhlman",
      "email": "Harvey.Stroman75@hotmail.com",
      "phone": "649.143.2673 x54716",
      "city": "Lake Waldofort",
      "country": "Poland",
      "title": "Investor Response Consultant"
    },
    {
      "id": 66,
      "firstName": "Levi",
      "lastName": "Kiehn",
      "email": "Libby.Mosciski@gmail.com",
      "phone": "1-918-745-7098 x60140",
      "city": "Niaton",
      "country": "Nepal",
      "title": "Product Infrastructure Officer"
    },
    {
      "id": 67,
      "firstName": "Tristian",
      "lastName": "Green",
      "email": "Helmer41@hotmail.com",
      "phone": "918-154-0541 x2885",
      "city": "McGlynnhaven",
      "country": "Syrian Arab Republic",
      "title": "Future Identity Planner"
    },
    {
      "id": 68,
      "firstName": "Noemie",
      "lastName": "Maggio",
      "email": "Jamel85@yahoo.com",
      "phone": "1-623-625-4903 x6090",
      "city": "Rashadland",
      "country": "Lithuania",
      "title": "Principal Brand Analyst"
    },
    {
      "id": 69,
      "firstName": "Torrance",
      "lastName": "Beer",
      "email": "Gladyce_Tromp@hotmail.com",
      "phone": "1-584-964-7884",
      "city": "Wallaceview",
      "country": "Iceland",
      "title": "Dynamic Solutions Facilitator"
    },
    {
      "id": 70,
      "firstName": "Ressie",
      "lastName": "Schmitt",
      "email": "Candace_Gleason71@hotmail.com",
      "phone": "016.339.1694",
      "city": "Lake Araceliland",
      "country": "Niue",
      "title": "Central Markets Supervisor"
    },
    {
      "id": 71,
      "firstName": "Marques",
      "lastName": "McKenzie",
      "email": "Vita.Moen52@yahoo.com",
      "phone": "321-515-2509 x0174",
      "city": "Lebsackland",
      "country": "Trinidad and Tobago",
      "title": "Principal Identity Agent"
    },
    {
      "id": 72,
      "firstName": "Madilyn",
      "lastName": "Stoltenberg",
      "email": "Sedrick.Romaguera@hotmail.com",
      "phone": "(422) 250-5719 x92112",
      "city": "Patfort",
      "country": "Malta",
      "title": "Dynamic Mobility Coordinator"
    },
    {
      "id": 73,
      "firstName": "Eliezer",
      "lastName": "Tillman",
      "email": "Aracely.Ankunding37@gmail.com",
      "phone": "406-881-6035 x195",
      "city": "Malachiville",
      "country": "Australia",
      "title": "Principal Marketing Assistant"
    },
    {
      "id": 74,
      "firstName": "Jefferey",
      "lastName": "Pacocha",
      "email": "Freeman_Runolfsson@gmail.com",
      "phone": "1-390-943-7596",
      "city": "North Annamarie",
      "country": "Eritrea",
      "title": "Dynamic Operations Agent"
    },
    {
      "id": 75,
      "firstName": "Sabryna",
      "lastName": "Anderson",
      "email": "Eddie_Reichert56@gmail.com",
      "phone": "(158) 397-0537",
      "city": "Effertzmouth",
      "country": "Benin",
      "title": "Customer Quality Engineer"
    },
    {
      "id": 76,
      "firstName": "Bailee",
      "lastName": "Zieme",
      "email": "Alexander_Stracke98@gmail.com",
      "phone": "(499) 721-3639 x3609",
      "city": "South Deronfort",
      "country": "Mayotte",
      "title": "Human Group Liaison"
    },
    {
      "id": 77,
      "firstName": "Vincenza",
      "lastName": "Berge",
      "email": "Liana_Kuhlman67@gmail.com",
      "phone": "774-308-9581 x339",
      "city": "North Ernie",
      "country": "Togo",
      "title": "Chief Brand Coordinator"
    },
    {
      "id": 78,
      "firstName": "Madeline",
      "lastName": "Zboncak",
      "email": "Merle80@hotmail.com",
      "phone": "(535) 861-5711 x2000",
      "city": "North Shanelle",
      "country": "Chad",
      "title": "Future Tactics Agent"
    },
    {
      "id": 79,
      "firstName": "Gregg",
      "lastName": "Wuckert",
      "email": "Narciso50@yahoo.com",
      "phone": "042-319-3241 x07912",
      "city": "East Jaleelchester",
      "country": "Yemen",
      "title": "Dynamic Communications Engineer"
    },
    {
      "id": 80,
      "firstName": "Juanita",
      "lastName": "Purdy",
      "email": "Nestor.Champlin@gmail.com",
      "phone": "1-053-510-4846 x10528",
      "city": "New Kurt",
      "country": "Montserrat",
      "title": "Future Infrastructure Strategist"
    },
    {
      "id": 81,
      "firstName": "Damien",
      "lastName": "Nitzsche",
      "email": "Lewis_Huels62@gmail.com",
      "phone": "1-666-618-6740 x7864",
      "city": "Kaceyberg",
      "country": "Bahrain",
      "title": "Forward Optimization Strategist"
    },
    {
      "id": 82,
      "firstName": "Kayli",
      "lastName": "Jacobson",
      "email": "Orin64@gmail.com",
      "phone": "1-175-053-6088",
      "city": "Ankundingland",
      "country": "El Salvador",
      "title": "Dynamic Creative Developer"
    },
    {
      "id": 83,
      "firstName": "Percy",
      "lastName": "Jacobi",
      "email": "Hannah34@hotmail.com",
      "phone": "(910) 610-2353 x3791",
      "city": "Rosaleestad",
      "country": "Hungary",
      "title": "Dynamic Web Specialist"
    },
    {
      "id": 84,
      "firstName": "Chanelle",
      "lastName": "Brakus",
      "email": "Dwight_Gerlach@gmail.com",
      "phone": "1-108-828-0352 x43064",
      "city": "New Emmett",
      "country": "Hong Kong",
      "title": "Central Solutions Coordinator"
    },
    {
      "id": 85,
      "firstName": "Dessie",
      "lastName": "Carroll",
      "email": "Scottie.OConnell@gmail.com",
      "phone": "788-330-5514",
      "city": "Halvorsonton",
      "country": "Singapore",
      "title": "Future Accounts Agent"
    },
    {
      "id": 86,
      "firstName": "Milan",
      "lastName": "Hamill",
      "email": "Mariane93@gmail.com",
      "phone": "1-326-931-7295 x75315",
      "city": "Terranceport",
      "country": "Haiti",
      "title": "Internal Interactions Assistant"
    },
    {
      "id": 87,
      "firstName": "Armand",
      "lastName": "Willms",
      "email": "Kevon_OKon94@yahoo.com",
      "phone": "085-370-6054",
      "city": "Agnesside",
      "country": "British Indian Ocean Territory (Chagos Archipelago)",
      "title": "Internal Assurance Orchestrator"
    },
    {
      "id": 88,
      "firstName": "Eliseo",
      "lastName": "Pollich",
      "email": "Lucie.Nicolas78@hotmail.com",
      "phone": "200.379.4672 x07466",
      "city": "Kaneport",
      "country": "Colombia",
      "title": "Internal Operations Administrator"
    },
    {
      "id": 89,
      "firstName": "Rebeca",
      "lastName": "Schaden",
      "email": "Xander.Friesen22@gmail.com",
      "phone": "1-412-498-9086",
      "city": "West Felicity",
      "country": "Kazakhstan",
      "title": "Chief Configuration Assistant"
    },
    {
      "id": 90,
      "firstName": "Janelle",
      "lastName": "O'Reilly",
      "email": "Kendra.Lindgren@yahoo.com",
      "phone": "130.674.5523",
      "city": "South Gerhard",
      "country": "Somalia",
      "title": "Chief Web Strategist"
    },
    {
      "id": 91,
      "firstName": "Darrick",
      "lastName": "Crooks",
      "email": "Grace26@gmail.com",
      "phone": "(015) 914-6444",
      "city": "East Gayle",
      "country": "Yemen",
      "title": "Investor Data Architect"
    },
    {
      "id": 92,
      "firstName": "Elwyn",
      "lastName": "Wintheiser",
      "email": "Gillian63@yahoo.com",
      "phone": "727-507-6146",
      "city": "Hildabury",
      "country": "Haiti",
      "title": "Dynamic Division Agent"
    },
    {
      "id": 93,
      "firstName": "Henri",
      "lastName": "Hyatt",
      "email": "Dallas_Boyer59@hotmail.com",
      "phone": "986.430.6233 x9665",
      "city": "Lake Daphney",
      "country": "Liberia",
      "title": "Global Usability Representative"
    },
    {
      "id": 94,
      "firstName": "Jannie",
      "lastName": "Swift",
      "email": "Imogene_Russel@hotmail.com",
      "phone": "622.140.5233 x79736",
      "city": "South Collinberg",
      "country": "San Marino",
      "title": "Chief Applications Analyst"
    },
    {
      "id": 95,
      "firstName": "Geraldine",
      "lastName": "Parisian",
      "email": "Tommie.Fritsch17@yahoo.com",
      "phone": "(185) 323-6833 x83479",
      "city": "Millermouth",
      "country": "Solomon Islands",
      "title": "Direct Security Analyst"
    },
    {
      "id": 96,
      "firstName": "Citlalli",
      "lastName": "Runolfsdottir",
      "email": "Ryann80@yahoo.com",
      "phone": "387.025.5088",
      "city": "Franzchester",
      "country": "French Southern Territories",
      "title": "Legacy Creative Planner"
    },
    {
      "id": 97,
      "firstName": "Dejon",
      "lastName": "Adams",
      "email": "Cooper.Krajcik@gmail.com",
      "phone": "(138) 072-1005 x4543",
      "city": "Lake Talon",
      "country": "Zimbabwe",
      "title": "Customer Marketing Assistant"
    },
    {
      "id": 98,
      "firstName": "Jordan",
      "lastName": "White",
      "email": "Colby.Gleichner@hotmail.com",
      "phone": "522-441-3956",
      "city": "Deontaeton",
      "country": "Niger",
      "title": "National Assurance Technician"
    },
    {
      "id": 99,
      "firstName": "Ernestine",
      "lastName": "Orn",
      "email": "Nellie41@gmail.com",
      "phone": "948-778-6632 x38672",
      "city": "Dibbertview",
      "country": "Virgin Islands, British",
      "title": "International Program Engineer"
    },
    {
      "id": 100,
      "firstName": "Earnest",
      "lastName": "Crist",
      "email": "Keyshawn_Schmidt@yahoo.com",
      "phone": "181.855.0186 x1071",
      "city": "Cassinburgh",
      "country": "Uruguay",
      "title": "Forward Accounts Assistant"
    },
    {
      "id": 101,
      "firstName": "Alfonzo",
      "lastName": "Kirlin",
      "email": "Fabiola64@yahoo.com",
      "phone": "(567) 954-5741",
      "city": "New Celestine",
      "country": "Switzerland",
      "title": "Dynamic Configuration Liaison"
    },
    {
      "id": 102,
      "firstName": "Bruce",
      "lastName": "Kris",
      "email": "Dorcas.Dicki17@yahoo.com",
      "phone": "(912) 853-2162",
      "city": "West Jenniferborough",
      "country": "Netherlands",
      "title": "Future Optimization Supervisor"
    },
    {
      "id": 103,
      "firstName": "Justen",
      "lastName": "Hudson",
      "email": "Sally16@yahoo.com",
      "phone": "(700) 943-4342",
      "city": "East Justinaton",
      "country": "Luxembourg",
      "title": "Investor Marketing Officer"
    },
    {
      "id": 104,
      "firstName": "Rodger",
      "lastName": "Veum",
      "email": "Andres.Runolfsson60@gmail.com",
      "phone": "955-846-8980",
      "city": "Terryfurt",
      "country": "Poland",
      "title": "Human Accountability Executive"
    },
    {
      "id": 105,
      "firstName": "Agnes",
      "lastName": "Hammes",
      "email": "Chad_Buckridge@hotmail.com",
      "phone": "491-542-1498 x737",
      "city": "Edhaven",
      "country": "Cape Verde",
      "title": "District Functionality Developer"
    },
    {
      "id": 106,
      "firstName": "Deontae",
      "lastName": "Conroy",
      "email": "Libby_Leffler68@hotmail.com",
      "phone": "(116) 923-9176 x657",
      "city": "Jairobury",
      "country": "Spain",
      "title": "Product Operations Executive"
    },
    {
      "id": 107,
      "firstName": "Mariane",
      "lastName": "Sawayn",
      "email": "Hiram_Kohler71@gmail.com",
      "phone": "1-718-687-4792 x40038",
      "city": "Adolffurt",
      "country": "Gabon",
      "title": "Central Operations Representative"
    },
    {
      "id": 108,
      "firstName": "Geovanni",
      "lastName": "Hickle",
      "email": "Kamille.Christiansen53@hotmail.com",
      "phone": "1-279-948-7081 x604",
      "city": "Larkinhaven",
      "country": "Cameroon",
      "title": "Global Group Analyst"
    },
    {
      "id": 109,
      "firstName": "Loraine",
      "lastName": "Lind",
      "email": "Coleman_Schulist69@yahoo.com",
      "phone": "981.231.9852 x369",
      "city": "Andreaneshire",
      "country": "Saint Vincent and the Grenadines",
      "title": "Corporate Intranet Coordinator"
    },
    {
      "id": 110,
      "firstName": "Oswaldo",
      "lastName": "Kutch",
      "email": "Tevin57@yahoo.com",
      "phone": "(060) 867-8126",
      "city": "New Christopheville",
      "country": "Algeria",
      "title": "Internal Web Analyst"
    },
    {
      "id": 111,
      "firstName": "Sarai",
      "lastName": "Quigley",
      "email": "Paxton_Lockman@hotmail.com",
      "phone": "764.561.4759",
      "city": "Port Kevon",
      "country": "Lebanon",
      "title": "Customer Response Specialist"
    },
    {
      "id": 112,
      "firstName": "Daisy",
      "lastName": "Renner",
      "email": "Mozelle7@gmail.com",
      "phone": "370-531-6224 x668",
      "city": "Lowehaven",
      "country": "Fiji",
      "title": "District Metrics Technician"
    },
    {
      "id": 113,
      "firstName": "Antonietta",
      "lastName": "Schoen",
      "email": "Hillary.Wisoky23@yahoo.com",
      "phone": "(602) 256-3422",
      "city": "Jerdestad",
      "country": "Sri Lanka",
      "title": "Customer Infrastructure Analyst"
    },
    {
      "id": 114,
      "firstName": "Alberto",
      "lastName": "Bogan",
      "email": "Vernon14@gmail.com",
      "phone": "1-510-932-9745",
      "city": "East Nayeli",
      "country": "Bhutan",
      "title": "Human Mobility Architect"
    },
    {
      "id": 115,
      "firstName": "Kassandra",
      "lastName": "Boyer",
      "email": "Merlin_Orn@hotmail.com",
      "phone": "237.032.2818 x4585",
      "city": "West Gerda",
      "country": "Comoros",
      "title": "Direct Research Orchestrator"
    },
    {
      "id": 116,
      "firstName": "Fidel",
      "lastName": "Armstrong",
      "email": "Tiffany_Dach11@hotmail.com",
      "phone": "373.531.9117 x552",
      "city": "West Rozellafurt",
      "country": "Maldives",
      "title": "National Brand Representative"
    },
    {
      "id": 117,
      "firstName": "Fae",
      "lastName": "Kessler",
      "email": "Ida.Purdy23@yahoo.com",
      "phone": "444.927.5926",
      "city": "Lake Jaclyn",
      "country": "Azerbaijan",
      "title": "Future Functionality Associate"
    },
    {
      "id": 118,
      "firstName": "Shania",
      "lastName": "Vandervort",
      "email": "Jarret49@gmail.com",
      "phone": "1-593-495-4549",
      "city": "Port Birdieland",
      "country": "Niger",
      "title": "District Solutions Assistant"
    },
    {
      "id": 119,
      "firstName": "Darrion",
      "lastName": "Cartwright",
      "email": "Eldon.Braun@yahoo.com",
      "phone": "373-299-0436 x03576",
      "city": "Leschville",
      "country": "Guernsey",
      "title": "Corporate Mobility Manager"
    },
    {
      "id": 120,
      "firstName": "Adeline",
      "lastName": "Parisian",
      "email": "Tanya_Conn53@yahoo.com",
      "phone": "036.270.9462 x3125",
      "city": "Pagacfurt",
      "country": "Netherlands",
      "title": "Direct Response Consultant"
    },
    {
      "id": 121,
      "firstName": "Zula",
      "lastName": "Bednar",
      "email": "Zoe.Conroy@hotmail.com",
      "phone": "149-467-6307 x09586",
      "city": "East Anaistown",
      "country": "Wallis and Futuna",
      "title": "Forward Integration Strategist"
    },
    {
      "id": 122,
      "firstName": "Gertrude",
      "lastName": "Funk",
      "email": "Cyrus65@gmail.com",
      "phone": "558-055-1869",
      "city": "Murazikmouth",
      "country": "Greece",
      "title": "Dynamic Accounts Strategist"
    },
    {
      "id": 123,
      "firstName": "Lindsey",
      "lastName": "Hilll",
      "email": "Claudia_West@yahoo.com",
      "phone": "841-480-9053 x67846",
      "city": "Daretown",
      "country": "Sri Lanka",
      "title": "Dynamic Configuration Specialist"
    },
    {
      "id": 124,
      "firstName": "Brendan",
      "lastName": "Zieme",
      "email": "Kamille_Shields61@yahoo.com",
      "phone": "1-581-641-6242",
      "city": "Rogerchester",
      "country": "Western Sahara",
      "title": "Principal Markets Liaison"
    },
    {
      "id": 125,
      "firstName": "Elinore",
      "lastName": "Rath",
      "email": "Dwight61@gmail.com",
      "phone": "085.448.8327 x139",
      "city": "Corwinborough",
      "country": "Saint Barthelemy",
      "title": "Human Integration Associate"
    },
    {
      "id": 126,
      "firstName": "Breanne",
      "lastName": "Flatley",
      "email": "Elaina.Heaney43@hotmail.com",
      "phone": "254.284.3489 x9691",
      "city": "Port Darrenburgh",
      "country": "Hungary",
      "title": "Direct Web Agent"
    },
    {
      "id": 127,
      "firstName": "Laney",
      "lastName": "Gutmann",
      "email": "Ramon.Robel@hotmail.com",
      "phone": "1-070-696-8884",
      "city": "South Hollis",
      "country": "Mali",
      "title": "Internal Factors Agent"
    },
    {
      "id": 128,
      "firstName": "Sammy",
      "lastName": "Corwin",
      "email": "Alexandria_Schowalter@hotmail.com",
      "phone": "1-101-022-0807 x66738",
      "city": "Clairville",
      "country": "Democratic People's Republic of Korea",
      "title": "Corporate Research Designer"
    },
    {
      "id": 129,
      "firstName": "Raul",
      "lastName": "Herman",
      "email": "Cody.McGlynn48@yahoo.com",
      "phone": "1-651-811-4328 x26632",
      "city": "New Aracelyfort",
      "country": "Sudan",
      "title": "Senior Data Technician"
    },
    {
      "id": 130,
      "firstName": "Magnolia",
      "lastName": "Streich",
      "email": "Muhammad.Swaniawski@gmail.com",
      "phone": "152-222-3489 x676",
      "city": "Russelmouth",
      "country": "Kazakhstan",
      "title": "Internal Brand Liaison"
    },
    {
      "id": 131,
      "firstName": "Willis",
      "lastName": "Welch",
      "email": "Kameron.Brakus80@yahoo.com",
      "phone": "652-594-2744 x138",
      "city": "Port Kasandraland",
      "country": "Somalia",
      "title": "Dynamic Brand Manager"
    },
    {
      "id": 132,
      "firstName": "Nelda",
      "lastName": "Waters",
      "email": "Titus66@gmail.com",
      "phone": "331-390-7624",
      "city": "Dickensmouth",
      "country": "South Georgia and the South Sandwich Islands",
      "title": "Forward Functionality Supervisor"
    },
    {
      "id": 133,
      "firstName": "Wilford",
      "lastName": "Leannon",
      "email": "Brandyn_Doyle56@gmail.com",
      "phone": "890.883.0296 x859",
      "city": "Gerhardburgh",
      "country": "Brunei Darussalam",
      "title": "Human Quality Developer"
    },
    {
      "id": 134,
      "firstName": "Gerardo",
      "lastName": "Predovic",
      "email": "Ivah_Gulgowski94@gmail.com",
      "phone": "089-180-0482 x77010",
      "city": "Einarview",
      "country": "Cyprus",
      "title": "Lead Usability Officer"
    },
    {
      "id": 135,
      "firstName": "Karianne",
      "lastName": "Rutherford",
      "email": "Casandra27@yahoo.com",
      "phone": "(714) 158-1625 x859",
      "city": "Christopstad",
      "country": "Tanzania",
      "title": "Human Tactics Officer"
    },
    {
      "id": 136,
      "firstName": "Nico",
      "lastName": "Mraz",
      "email": "Rusty30@hotmail.com",
      "phone": "1-607-274-6777 x50299",
      "city": "East August",
      "country": "Mali",
      "title": "Senior Mobility Associate"
    },
    {
      "id": 137,
      "firstName": "Cleveland",
      "lastName": "Carter",
      "email": "Reva_Stoltenberg77@yahoo.com",
      "phone": "098.614.9713",
      "city": "West Brett",
      "country": "Congo",
      "title": "Forward Research Supervisor"
    },
    {
      "id": 138,
      "firstName": "Pierre",
      "lastName": "Gleason",
      "email": "Freeman94@gmail.com",
      "phone": "1-127-414-6397 x7376",
      "city": "DuBuquefurt",
      "country": "Dominican Republic",
      "title": "Customer Integration Executive"
    },
    {
      "id": 139,
      "firstName": "Karine",
      "lastName": "Crooks",
      "email": "Alize55@gmail.com",
      "phone": "005-109-2307",
      "city": "Marvinstad",
      "country": "Eritrea",
      "title": "Principal Factors Administrator"
    },
    {
      "id": 140,
      "firstName": "Jackeline",
      "lastName": "Kuphal",
      "email": "Mauricio.Ondricka@gmail.com",
      "phone": "1-349-114-1334",
      "city": "West Metaburgh",
      "country": "Albania",
      "title": "Corporate Division Analyst"
    },
    {
      "id": 141,
      "firstName": "Shaun",
      "lastName": "Waelchi",
      "email": "Clare55@hotmail.com",
      "phone": "(649) 444-4918",
      "city": "East Hipolitoland",
      "country": "Cote d'Ivoire",
      "title": "Global Division Administrator"
    },
    {
      "id": 142,
      "firstName": "Ivory",
      "lastName": "Braun",
      "email": "Dejah.Kemmer@yahoo.com",
      "phone": "949.495.4208 x8282",
      "city": "South Gladysberg",
      "country": "Nepal",
      "title": "Legacy Web Consultant"
    },
    {
      "id": 143,
      "firstName": "Sabryna",
      "lastName": "Wyman",
      "email": "Bell_Powlowski@gmail.com",
      "phone": "120.853.1857 x6859",
      "city": "Hauckmouth",
      "country": "Andorra",
      "title": "Senior Marketing Director"
    },
    {
      "id": 144,
      "firstName": "Dayna",
      "lastName": "Feest",
      "email": "Norris_Witting@gmail.com",
      "phone": "(316) 015-5691",
      "city": "East Ronville",
      "country": "Slovakia (Slovak Republic)",
      "title": "Product Intranet Analyst"
    },
    {
      "id": 145,
      "firstName": "Emmie",
      "lastName": "Breitenberg",
      "email": "Filomena.Bogan@yahoo.com",
      "phone": "201-362-5714 x34465",
      "city": "Hamillton",
      "country": "Equatorial Guinea",
      "title": "National Accountability Representative"
    },
    {
      "id": 146,
      "firstName": "Kali",
      "lastName": "Glover",
      "email": "Brennon.Trantow70@gmail.com",
      "phone": "506.071.6920 x462",
      "city": "South Lewmouth",
      "country": "Bolivia",
      "title": "Principal Tactics Assistant"
    },
    {
      "id": 147,
      "firstName": "Treva",
      "lastName": "Brekke",
      "email": "Leanna.Schoen@hotmail.com",
      "phone": "469.624.5582 x8409",
      "city": "Flatleyborough",
      "country": "Vietnam",
      "title": "Dynamic Web Specialist"
    },
    {
      "id": 148,
      "firstName": "Kayli",
      "lastName": "Tremblay",
      "email": "Antonetta_Beatty71@hotmail.com",
      "phone": "(603) 571-4663 x274",
      "city": "Warrenchester",
      "country": "Comoros",
      "title": "Future Factors Producer"
    },
    {
      "id": 149,
      "firstName": "Arlie",
      "lastName": "Olson",
      "email": "Lori_Muller86@gmail.com",
      "phone": "777-057-1379 x83517",
      "city": "Adrianchester",
      "country": "Liechtenstein",
      "title": "Product Communications Manager"
    },
    {
      "id": 150,
      "firstName": "Jamey",
      "lastName": "Kshlerin",
      "email": "Estell43@hotmail.com",
      "phone": "1-068-186-6097",
      "city": "South Wilford",
      "country": "Botswana",
      "title": "Regional Optimization Supervisor"
    },
    {
      "id": 151,
      "firstName": "Darwin",
      "lastName": "Haag",
      "email": "Miracle_Pfeffer6@hotmail.com",
      "phone": "721.723.8598 x85441",
      "city": "Dachland",
      "country": "Cambodia",
      "title": "Product Quality Planner"
    },
    {
      "id": 152,
      "firstName": "Chadd",
      "lastName": "Hilpert",
      "email": "Kayden_Davis52@hotmail.com",
      "phone": "(138) 344-8169",
      "city": "New Carlieland",
      "country": "Denmark",
      "title": "Chief Infrastructure Supervisor"
    },
    {
      "id": 153,
      "firstName": "Shane",
      "lastName": "Bartell",
      "email": "Tyra.Mraz71@hotmail.com",
      "phone": "151-304-6171",
      "city": "Port Tamarafurt",
      "country": "Aruba",
      "title": "Product Markets Consultant"
    },
    {
      "id": 154,
      "firstName": "Melisa",
      "lastName": "O'Connell",
      "email": "Anika.Christiansen83@gmail.com",
      "phone": "(477) 019-0444 x0245",
      "city": "North Bertrandland",
      "country": "Jamaica",
      "title": "Investor Paradigm Facilitator"
    },
    {
      "id": 155,
      "firstName": "Henry",
      "lastName": "Rempel",
      "email": "Mariano67@yahoo.com",
      "phone": "338-652-6161 x785",
      "city": "Kuhnside",
      "country": "Sierra Leone",
      "title": "Future Mobility Facilitator"
    },
    {
      "id": 156,
      "firstName": "Frederique",
      "lastName": "Carroll",
      "email": "Maxie.Ankunding32@hotmail.com",
      "phone": "(244) 617-5659 x93939",
      "city": "Connellyport",
      "country": "Sierra Leone",
      "title": "Global Marketing Analyst"
    },
    {
      "id": 157,
      "firstName": "Arch",
      "lastName": "Dietrich",
      "email": "Saul_Beer@yahoo.com",
      "phone": "1-604-413-3325 x51384",
      "city": "Darylton",
      "country": "France",
      "title": "Customer Creative Analyst"
    },
    {
      "id": 158,
      "firstName": "Rafaela",
      "lastName": "Goldner",
      "email": "Graciela3@gmail.com",
      "phone": "477-797-2333 x4749",
      "city": "Hegmannton",
      "country": "Guinea",
      "title": "Central Security Engineer"
    },
    {
      "id": 159,
      "firstName": "Bettie",
      "lastName": "Dickens",
      "email": "Lela_Hauck@yahoo.com",
      "phone": "1-768-436-9530",
      "city": "New Abeltown",
      "country": "Central African Republic",
      "title": "Forward Tactics Orchestrator"
    },
    {
      "id": 160,
      "firstName": "Keagan",
      "lastName": "Metz",
      "email": "Myles92@hotmail.com",
      "phone": "126-519-3575",
      "city": "Port Modesto",
      "country": "Oman",
      "title": "Direct Markets Engineer"
    },
    {
      "id": 161,
      "firstName": "Madie",
      "lastName": "Gottlieb",
      "email": "Charley6@yahoo.com",
      "phone": "453-765-3066 x363",
      "city": "Collinsmouth",
      "country": "Comoros",
      "title": "Chief Creative Architect"
    },
    {
      "id": 162,
      "firstName": "Rosanna",
      "lastName": "Shanahan",
      "email": "Lorna.Fritsch4@hotmail.com",
      "phone": "1-423-579-3940 x183",
      "city": "South Norval",
      "country": "Burkina Faso",
      "title": "Future Functionality Associate"
    },
    {
      "id": 163,
      "firstName": "Norwood",
      "lastName": "Rippin",
      "email": "Tevin_Fritsch@gmail.com",
      "phone": "1-750-616-6908 x87916",
      "city": "Isaacshire",
      "country": "Netherlands Antilles",
      "title": "District Data Facilitator"
    },
    {
      "id": 164,
      "firstName": "Jules",
      "lastName": "Stracke",
      "email": "Glenda21@gmail.com",
      "phone": "(968) 857-8635",
      "city": "Lake Chynaside",
      "country": "Guam",
      "title": "Internal Assurance Developer"
    },
    {
      "id": 165,
      "firstName": "Cade",
      "lastName": "Wolf",
      "email": "Silas_Yundt@gmail.com",
      "phone": "017.887.7432 x8447",
      "city": "North Destini",
      "country": "Heard Island and McDonald Islands",
      "title": "Regional Factors Facilitator"
    },
    {
      "id": 166,
      "firstName": "Leonie",
      "lastName": "Bernier",
      "email": "Mazie.Keebler@gmail.com",
      "phone": "(000) 731-9767 x21005",
      "city": "Lake Allen",
      "country": "France",
      "title": "Product Division Supervisor"
    },
    {
      "id": 167,
      "firstName": "Arlo",
      "lastName": "Williamson",
      "email": "Tess_Gusikowski@hotmail.com",
      "phone": "(361) 519-1018 x31936",
      "city": "Trantowbury",
      "country": "South Africa",
      "title": "Legacy Division Director"
    },
    {
      "id": 168,
      "firstName": "Cali",
      "lastName": "Mohr",
      "email": "Oliver_Murphy@hotmail.com",
      "phone": "1-516-618-8248",
      "city": "West Alphonso",
      "country": "Senegal",
      "title": "District Usability Consultant"
    },
    {
      "id": 169,
      "firstName": "Stan",
      "lastName": "Hackett",
      "email": "Logan.Larkin@hotmail.com",
      "phone": "1-829-576-2744 x3806",
      "city": "Hilperthaven",
      "country": "Dominica",
      "title": "Dynamic Factors Director"
    },
    {
      "id": 170,
      "firstName": "Emmett",
      "lastName": "Bayer",
      "email": "Alfred49@hotmail.com",
      "phone": "(495) 768-9625 x672",
      "city": "Port Thoraburgh",
      "country": "Spain",
      "title": "Senior Web Specialist"
    },
    {
      "id": 171,
      "firstName": "Shirley",
      "lastName": "Effertz",
      "email": "Athena37@hotmail.com",
      "phone": "109.814.3837 x59143",
      "city": "Eliseoshire",
      "country": "Peru",
      "title": "Dynamic Web Assistant"
    },
    {
      "id": 172,
      "firstName": "Elliot",
      "lastName": "Kreiger",
      "email": "Aidan_Rolfson@hotmail.com",
      "phone": "(628) 656-0173 x713",
      "city": "West Micaela",
      "country": "Saint Martin",
      "title": "Principal Configuration Officer"
    },
    {
      "id": 173,
      "firstName": "Chanel",
      "lastName": "Lubowitz",
      "email": "Ella.Barrows93@gmail.com",
      "phone": "537-023-2651 x171",
      "city": "Watersfort",
      "country": "Ireland",
      "title": "Lead Configuration Designer"
    },
    {
      "id": 174,
      "firstName": "Caleigh",
      "lastName": "Bahringer",
      "email": "Jessica43@yahoo.com",
      "phone": "1-296-742-3838 x04794",
      "city": "Demarcochester",
      "country": "Martinique",
      "title": "Senior Marketing Supervisor"
    },
    {
      "id": 175,
      "firstName": "Jaren",
      "lastName": "McClure",
      "email": "Destin8@hotmail.com",
      "phone": "1-516-630-1695 x93974",
      "city": "Magalitown",
      "country": "Bouvet Island (Bouvetoya)",
      "title": "Internal Data Supervisor"
    },
    {
      "id": 176,
      "firstName": "Eda",
      "lastName": "McDermott",
      "email": "Arden.Langosh@hotmail.com",
      "phone": "(637) 871-1898",
      "city": "Caspermouth",
      "country": "Turks and Caicos Islands",
      "title": "Global Usability Consultant"
    },
    {
      "id": 177,
      "firstName": "Gabe",
      "lastName": "Weissnat",
      "email": "Tremaine85@yahoo.com",
      "phone": "(168) 983-1970",
      "city": "Metzmouth",
      "country": "Holy See (Vatican City State)",
      "title": "Dynamic Operations Supervisor"
    },
    {
      "id": 178,
      "firstName": "Emery",
      "lastName": "Weimann",
      "email": "Gerard_Considine30@hotmail.com",
      "phone": "1-751-341-4730 x9127",
      "city": "Schillerborough",
      "country": "Maldives",
      "title": "Central Communications Producer"
    },
    {
      "id": 179,
      "firstName": "Marley",
      "lastName": "Cronin",
      "email": "Kacey.Swift60@hotmail.com",
      "phone": "704-944-2768 x837",
      "city": "Lake Alvisfort",
      "country": "Belgium",
      "title": "Internal Markets Associate"
    },
    {
      "id": 180,
      "firstName": "Haylee",
      "lastName": "Russel",
      "email": "Bernadette.Kunze@gmail.com",
      "phone": "(991) 503-4515",
      "city": "Prosaccobury",
      "country": "Colombia",
      "title": "Senior Tactics Executive"
    },
    {
      "id": 181,
      "firstName": "Janie",
      "lastName": "Klocko",
      "email": "Pinkie_Robel55@gmail.com",
      "phone": "193-987-0461 x239",
      "city": "Port Eleonoreborough",
      "country": "New Caledonia",
      "title": "Regional Group Technician"
    },
    {
      "id": 182,
      "firstName": "Brannon",
      "lastName": "Funk",
      "email": "Chanel_Grant@hotmail.com",
      "phone": "1-399-893-5929",
      "city": "Javonton",
      "country": "Costa Rica",
      "title": "Direct Assurance Producer"
    },
    {
      "id": 183,
      "firstName": "Ashton",
      "lastName": "Rogahn",
      "email": "Antonina_Harvey@gmail.com",
      "phone": "1-047-115-3262",
      "city": "Sheilahaven",
      "country": "Niue",
      "title": "Investor Accountability Director"
    },
    {
      "id": 184,
      "firstName": "Betty",
      "lastName": "Schmitt",
      "email": "Maxwell_Olson@yahoo.com",
      "phone": "123-170-1850 x6964",
      "city": "East Orlando",
      "country": "Mauritius",
      "title": "Customer Intranet Liaison"
    },
    {
      "id": 185,
      "firstName": "Winifred",
      "lastName": "Bogan",
      "email": "General76@hotmail.com",
      "phone": "567-387-1526 x839",
      "city": "Bruenfurt",
      "country": "Cayman Islands",
      "title": "International Paradigm Representative"
    },
    {
      "id": 186,
      "firstName": "Darian",
      "lastName": "Berge",
      "email": "Hilma19@yahoo.com",
      "phone": "1-223-124-6235 x8890",
      "city": "Kerlukechester",
      "country": "Luxembourg",
      "title": "Forward Configuration Officer"
    },
    {
      "id": 187,
      "firstName": "Sadie",
      "lastName": "Leuschke",
      "email": "Darrick45@yahoo.com",
      "phone": "545.050.2510 x4386",
      "city": "Hansfurt",
      "country": "Serbia",
      "title": "Dynamic Applications Coordinator"
    },
    {
      "id": 188,
      "firstName": "Theron",
      "lastName": "Glover",
      "email": "Flavie.Greenfelder37@gmail.com",
      "phone": "095.889.3387 x724",
      "city": "New Kentonside",
      "country": "Belize",
      "title": "Future Integration Specialist"
    },
    {
      "id": 189,
      "firstName": "Noel",
      "lastName": "Zemlak",
      "email": "Otto_Trantow6@hotmail.com",
      "phone": "(582) 619-5708 x952",
      "city": "Erdmanside",
      "country": "French Guiana",
      "title": "Product Functionality Executive"
    },
    {
      "id": 190,
      "firstName": "Wilfredo",
      "lastName": "Runolfsdottir",
      "email": "Elenor79@gmail.com",
      "phone": "143-345-4902 x3114",
      "city": "North Brodyfurt",
      "country": "Guinea",
      "title": "Forward Infrastructure Engineer"
    },
    {
      "id": 191,
      "firstName": "Keara",
      "lastName": "Predovic",
      "email": "Gwendolyn42@gmail.com",
      "phone": "695-347-3252",
      "city": "Kertzmannville",
      "country": "Malawi",
      "title": "Corporate Intranet Analyst"
    },
    {
      "id": 192,
      "firstName": "Hosea",
      "lastName": "Green",
      "email": "Verner88@yahoo.com",
      "phone": "1-029-267-5745",
      "city": "Dachland",
      "country": "Macedonia",
      "title": "District Optimization Administrator"
    },
    {
      "id": 193,
      "firstName": "Enos",
      "lastName": "Roob",
      "email": "Sister27@gmail.com",
      "phone": "504.864.0564",
      "city": "Larsonchester",
      "country": "Grenada",
      "title": "Senior Functionality Strategist"
    },
    {
      "id": 194,
      "firstName": "Daren",
      "lastName": "Stiedemann",
      "email": "Judge_Hintz@yahoo.com",
      "phone": "991.749.1957",
      "city": "Millschester",
      "country": "Cameroon",
      "title": "Central Implementation Liaison"
    },
    {
      "id": 195,
      "firstName": "Krystal",
      "lastName": "Lehner",
      "email": "Darrel.Rolfson34@yahoo.com",
      "phone": "385.321.4154 x4298",
      "city": "Georgetteport",
      "country": "Kenya",
      "title": "Direct Mobility Technician"
    },
    {
      "id": 196,
      "firstName": "Beulah",
      "lastName": "Schumm",
      "email": "Geraldine_Mueller@hotmail.com",
      "phone": "(644) 254-8214",
      "city": "Mitchellberg",
      "country": "Palau",
      "title": "Direct Markets Designer"
    },
    {
      "id": 197,
      "firstName": "Era",
      "lastName": "Labadie",
      "email": "Antonette80@hotmail.com",
      "phone": "190-851-7164 x8096",
      "city": "New Jailyn",
      "country": "Gambia",
      "title": "Dynamic Interactions Specialist"
    },
    {
      "id": 198,
      "firstName": "Reilly",
      "lastName": "Kuphal",
      "email": "Marques53@yahoo.com",
      "phone": "659-328-0964",
      "city": "Nicholausside",
      "country": "Myanmar",
      "title": "Direct Data Technician"
    },
    {
      "id": 199,
      "firstName": "Ethel",
      "lastName": "Rippin",
      "email": "Berta.Armstrong@gmail.com",
      "phone": "1-097-082-8915 x89026",
      "city": "Port Nehaport",
      "country": "Hungary",
      "title": "National Creative Designer"
    },
    {
      "id": 200,
      "firstName": "Marjolaine",
      "lastName": "Weissnat",
      "email": "Shane.Mayer6@hotmail.com",
      "phone": "1-849-450-0060",
      "city": "Johannaborough",
      "country": "Sierra Leone",
      "title": "District Security Administrator"
    },
    {
      "{\"firstName\":\"Shannon\", \"lastName\":\"Nitzsche\", \"email\":\"Hillary21@hotmail.com\", \"phone\":\"905 555-55-55\", \"city\":\"Milan\", \"country\":\"Italy\", \"title\":\"Mrs\"}": "",
      "id": 202
    },
    {
      "{'firstName':'Shannon', 'lastName':'Nitzsche', 'email':'Hillary21@hotmail.com', 'phone':'905 555-55-55', 'city':'Milan', 'country':'Italy', 'title':'Mrs'}": "",
      "id": 203
    },
    {
      "firstName": "Shannon",
      "lastName": "Nitzsche",
      "emaiL": "Hillary21@hotmail.com",
      "phone": "905 555-55-55",
      "city": "Milan",
      "country": "Italy",
      "title": "Mrs",
      "id": 204
    },
    {
      "city": "Miss",
      "lastName": "Rodriguez",
      "firstName": "Jorge",
      "email": "barizonte@gmail.com",
      "phone": "14564560990",
      "country": null,
      "title": null,
      "id": 205
    }
  ]
}